quickdate/__init__.py
quickdate/quickdate.py
quickdate-0.0.3.dist-info/LICENSE
quickdate-0.0.3.dist-info/METADATA
quickdate-0.0.3.dist-info/WHEEL
quickdate-0.0.3.dist-info/top_level.txt
quickdate-0.0.3.dist-info/RECORD
