Metadata-Version: 2.1
Name: quickdate
Version: 0.0.3
Summary: 快捷处理日期的Python库, 支持从字符串解析日期, 灵活实现加减日、周、月、年、时、分、秒的时间操作
Home-page: https://github.com/cador/quickdate
Author: Haolin You
Author-email: cador.ai@aliyun.com
License-File: LICENSE
Requires-Dist: datetime
Requires-Dist: python-dateutil
